dockerclassifier/__init__.py
dockerclassifier/classify.py
dockerclassifier-0.0.4.dist-info/LICENSE
dockerclassifier-0.0.4.dist-info/METADATA
dockerclassifier-0.0.4.dist-info/WHEEL
dockerclassifier-0.0.4.dist-info/top_level.txt
dockerclassifier-0.0.4.dist-info/RECORD
