Metadata-Version: 2.1
Name: dockerclassifier
Version: 0.0.4
Summary: A small, Docker-backed image recognition library
Home-page: https://github.com/pypa/sampleproject
Author: Gregory Wint
Author-email: gregwint95@gmail.com
License: UNKNOWN
Platform: UNKNOWN
Classifier: Programming Language :: Python :: 3
Classifier: License :: OSI Approved :: MIT License
Classifier: Operating System :: OS Independent
Requires-Python: >=3.6
